odoo/addons/base_tier_validation_definition_server_action/README.rst
odoo/addons/base_tier_validation_definition_server_action/__init__.py
odoo/addons/base_tier_validation_definition_server_action/__manifest__.py
odoo/addons/base_tier_validation_definition_server_action/i18n/base_tier_validation_definition_server_action.pot
odoo/addons/base_tier_validation_definition_server_action/i18n/es.po
odoo/addons/base_tier_validation_definition_server_action/i18n/it.po
odoo/addons/base_tier_validation_definition_server_action/models/__init__.py
odoo/addons/base_tier_validation_definition_server_action/models/tier_definition.py
odoo/addons/base_tier_validation_definition_server_action/models/tier_validation.py
odoo/addons/base_tier_validation_definition_server_action/readme/CONFIGURE.rst
odoo/addons/base_tier_validation_definition_server_action/readme/CONTRIBUTORS.rst
odoo/addons/base_tier_validation_definition_server_action/readme/DESCRIPTION.rst
odoo/addons/base_tier_validation_definition_server_action/static/description/icon.png
odoo/addons/base_tier_validation_definition_server_action/static/description/index.html
odoo/addons/base_tier_validation_definition_server_action/tests/__init__.py
odoo/addons/base_tier_validation_definition_server_action/tests/test_tier_validation.py
odoo/addons/base_tier_validation_definition_server_action/views/tier_definition_view.xml
odoo_addon_base_tier_validation_definition_server_action-16.0.1.0.0.7.dist-info/METADATA
odoo_addon_base_tier_validation_definition_server_action-16.0.1.0.0.7.dist-info/WHEEL
odoo_addon_base_tier_validation_definition_server_action-16.0.1.0.0.7.dist-info/top_level.txt
odoo_addon_base_tier_validation_definition_server_action-16.0.1.0.0.7.dist-info/RECORD
