Metadata-Version: 2.1
Name: odoo-addon-base-tier-validation-definition-server-action
Version: 16.0.1.0.0.7
Summary: Server action for Base tier validation
Home-page: https://github.com/OCA/server-ux
Author: ForgeFlow,Odoo Community Association (OCA)
Author-email: support@odoo-community.org
License: AGPL-3
Platform: UNKNOWN
Classifier: Programming Language :: Python
Classifier: Framework :: Odoo
Classifier: Framework :: Odoo :: 16.0
Classifier: License :: OSI Approved :: GNU Affero General Public License v3
Requires-Python: >=3.10
Requires-Dist: odoo-addon-base-tier-validation <16.1dev,>=16.0dev
Requires-Dist: odoo <16.1dev,>=16.0a
